ants
helpers
mybi-ci-meta
server
validators
